{"cameraMode":{"drawMode":0,"name":"Shaded","section":"Shading Mode"},"sceneLighting":true,"audioPlay":false,"sceneViewState":{"m_AlwaysRefresh":false,"showFog":true,"showSkybox":true,"showFlares":true,"showImageEffects":true,"showParticleSystems":true,"showVisualEffectGraphs":true,"m_FxEnabled":true},"in2DMode":false,"pivot":{"x":-18.159713745117189,"y":-16.739656448364259,"z":9.968509674072266},"rotation":{"x":-0.2721635699272156,"y":0.5145161151885986,"z":-0.17641392350196839,"w":-0.7937811017036438},"size":17.763113021850587,"orthographic":false}